object_repr/__init__.py
object_repr/object_repr.py
object_repr-0.0.2.dist-info/LICENSE.txt
object_repr-0.0.2.dist-info/METADATA
object_repr-0.0.2.dist-info/WHEEL
object_repr-0.0.2.dist-info/top_level.txt
object_repr-0.0.2.dist-info/RECORD
